README.md
setup.py
LPP0D.egg-info/PKG-INFO
LPP0D.egg-info/SOURCES.txt
LPP0D.egg-info/dependency_links.txt
LPP0D.egg-info/not-zip-safe
LPP0D.egg-info/top_level.txt
backend/Ploss_hardcoded.py
backend/__init__.py
backend/diff_generator.py
backend/molar_masses.py
backend/molarread.py
backend/objects_generator.py
backend/rates.py
backend/solve_and_post_proc.py
backend/toolbox_functions.py
frontend/__init__.py
frontend/generated_diff.py
frontend/main.py
frontend/main_Chabert2012.py
frontend/main_Grondein2016.py